pixi_rocker/__init__.py
pixi_rocker/pixi.py
pixi_rocker/templates/curl_snippet.Dockerfile
pixi_rocker/templates/pixi_snippet.Dockerfile
pixi_rocker-0.0.9.dist-info/METADATA
pixi_rocker-0.0.9.dist-info/WHEEL
pixi_rocker-0.0.9.dist-info/entry_points.txt
pixi_rocker-0.0.9.dist-info/licenses/LICENSE
pixi_rocker-0.0.9.dist-info/RECORD
